server_api/__init__.py
server_api/config.py
server_api/models.py
server_api/requests.py
server_api/utils.py
kubanemil_server_api-0.1.0.dist-info/LICENSE.txt
kubanemil_server_api-0.1.0.dist-info/METADATA
kubanemil_server_api-0.1.0.dist-info/WHEEL
kubanemil_server_api-0.1.0.dist-info/top_level.txt
kubanemil_server_api-0.1.0.dist-info/RECORD
