Metadata-Version: 2.1
Name: kubanemil-server-api
Version: 0.1.0
Home-page: https://git-codecommit.eu-central-1.amazonaws.com/v1/repos/server-api
Author: Kuban Emil
Author-email: emil3toktobekov@gmail.com
License-File: LICENSE.txt
Requires-Dist: requests (==2.31.0)
Requires-Dist: sqlmodel (==0.0.8)
Requires-Dist: pydantic (<2,>=1.10.12)
